pdm_dockerize-0.6.0.dist-info/METADATA
pdm_dockerize-0.6.0.dist-info/WHEEL
pdm_dockerize-0.6.0.dist-info/entry_points.txt
pdm_dockerize-0.6.0.dist-info/licenses/LICENSE
pdm_dockerize/VERSION
pdm_dockerize/__init__.py
pdm_dockerize/commands.py
pdm_dockerize/config.py
pdm_dockerize/entrypoint.py
pdm_dockerize/filters.py
pdm_dockerize/installer.py
pdm_dockerize/py.typed
pdm_dockerize-0.6.0.dist-info/RECORD
