Metadata-Version: 2.1
Name: pdm-dockerize
Version: 0.6.0
Summary: Help generating docker images from PDM projects
Author-Email: Axel Haustant <noirbizarre@gmail.com>
License: MIT
Classifier: Development Status :: 4 - Beta
Classifier: Environment :: Plugins
Classifier: Intended Audience :: Developers
Classifier: Programming Language :: Python
Classifier: Programming Language :: Python :: 3
Classifier: Programming Language :: Python :: 3 :: Only
Classifier: Programming Language :: Python :: 3.8
Classifier: Programming Language :: Python :: 3.9
Classifier: Programming Language :: Python :: 3.10
Classifier: Programming Language :: Python :: 3.11
Classifier: Programming Language :: Python :: 3.12
Classifier: Topic :: Software Development
Classifier: Topic :: Software Development :: Build Tools
Classifier: Topic :: Software Development :: Code Generators
Classifier: Typing :: Typed
Project-URL: Homepage, https://github.com/noirbizarre/pdm-dockerize
Project-URL: Documentation, https://github.com/noirbizarre/pdm-dockerize#readme
Project-URL: Repository, https://github.com/noirbizarre/pdm-dockerize
Project-URL: Issues, https://github.com/noirbizarre/pdm-dockerize/issues
Requires-Python: >=3.8.1
Requires-Dist: pdm>=2.19
